spectrumCatcher/__init__.py
spectrumCatcher/downloader.py
spectrumCatcher/processor.py
spectrumCatcher/some_function.py
spectrumCatcher-0.1.0.dist-info/METADATA
spectrumCatcher-0.1.0.dist-info/WHEEL
spectrumCatcher-0.1.0.dist-info/top_level.txt
spectrumCatcher-0.1.0.dist-info/RECORD
