Metadata-Version: 2.1
Name: spectrumCatcher
Version: 0.1.0
Summary: This is a Python library for downloading & analyzing Spectrum Catcher Data with Python.
Home-page: UNKNOWN
Author: Garid Zorigoo
Author-email: UNKNOWN
License: MIT
Platform: UNKNOWN
